jhvar/__init__.py
jhvar/django/__init__.py
jhvar/django/urls/__init__.py
jhvar/django/urls/middleware/__init__.py
jhvar/django/utils/__init__.py
django_role_router-0.2.1.dist-info/LICENSE
django_role_router-0.2.1.dist-info/METADATA
django_role_router-0.2.1.dist-info/WHEEL
django_role_router-0.2.1.dist-info/top_level.txt
django_role_router-0.2.1.dist-info/RECORD
