Metadata-Version: 2.1
Name: django-role-router
Version: 0.2.1
Summary: Make django router with role permission
Home-page: https://github.com/jhvar/django-utils
Author: jhvar
Author-email: jhvar@outlook.com
License: MIT Licence
Keywords: pip,django,role,util
Platform: UNKNOWN
Classifier: Programming Language :: Python :: 3
Classifier: License :: OSI Approved :: MIT License
Classifier: Operating System :: OS Independent
Requires-Python: >=3.6
Requires-Dist: django (>=2.2.5)
